<?xml version="1.0" encoding="UTF-8"?>
<openerp>
	<data>

		<!-- الطلبات -->

		<record model="ir.ui.view" id="hr_holidays_tree">
			<field name="name">hr.holidays.tree</field>
			<field name="model">hr.holidays</field>
			<field name="type">tree</field>
			<field name="inherit_id" ref="hr_holidays.view_holiday_allocation_tree" />
			<field name="arch" type="xml">
				<xpath expr="/tree" position='replace'>
					<tree string="الطلبات">
						<field name="name" string = "الرمز" />
						<field name="employee_id" />
						<field name="holiday_status_id" />
						<field name="date_from" />
						<field name="date_to" />
						<field name="state" />
					</tree>
				</xpath>
			</field>
		</record>

		<record model="ir.ui.view" id="hr_holidays_form">
			<field name="name">hr.holidays.form</field>
			<field name="model">hr.holidays</field>
			<field name="type">form</field>
			<field name="arch" type="xml">
				<form string="الطلبات">
					<field name="is_current_user" invisible="1" />
					<header name="main">
						<button name="send_holiday_request" string="إرسال طلب"
							type="object"
							attrs="{'invisible':['|',('state','!=','draft'),('is_current_user','=',False)]}"
							icon="fa-paper-plane" class="oe_inline oe_stat_button"
							confirm="هل أنت متأكد من القيام بهذا الإجراء ؟" />

						<button name="button_accept_dm" string="موافق" type="object"
							states="dm" groups="smart_hr.group_dm" icon="fa-check"
							class="oe_inline oe_stat_button" confirm="هل أنت متأكد من القيام بهذا الإجراء ؟" />

						<button name="action_delay_holiday" string="تأجيل" type="object"
							states="dm" groups="smart_hr.group_dm" icon="fa-times"
							class="oe_inline oe_stat_button" />

						<button name="button_accept_audit" string="موافق" type="object"
							states="audit" groups="smart_hr.group_holidays_checker" icon="fa-check"
							class="oe_inline oe_stat_button" confirm="هل أنت متأكد من القيام بهذا الإجراء ؟" />

						<button name="button_refuse_audit" string="رفض" type="object"
							states="audit" groups="smart_hr.group_holidays_checker" icon="fa-times"
							class="oe_inline oe_stat_button" />

						<button name="button_accept_hrm" string="موافق" type="object"
							states="hrm" groups="smart_hr.group_hrm" icon="fa-check"
							class="oe_inline oe_stat_button" confirm="هل أنت متأكد من القيام بهذا الإجراء ؟" />

						<button name="button_accept_external_audit" string="موافق"
							type="object" states="external_audit" groups="smart_hr.group_holidays_checker"
							icon="fa-check" class="oe_inline oe_stat_button" confirm="هل أنت متأكد من القيام بهذا الإجراء ؟" />

						<button name="button_refuse_external_audit" string="رفض"
							type="object" states="external_audit" groups="smart_hr.group_holidays_checker"
							icon="fa-times" class="oe_inline oe_stat_button" />

						<button name="button_accept_revision" string="موافق" type="object"
							states="revision" groups="smart_hr.group_director_division_salaries_vacations"
							icon="fa-check" class="oe_inline oe_stat_button" confirm="هل أنت متأكد من القيام بهذا الإجراء ؟" />

						<button name="button_refuse_revision" string="رفض" type="object"
							states="revision" groups="smart_hr.group_director_division_salaries_vacations"
							icon="fa-times" class="oe_inline oe_stat_button" />

						<button name="button_accept_revision_response" string="موافق"
							type="object" states="revision_response" groups="smart_hr.group_holidays_checker"
							icon="fa-times" class="oe_inline oe_stat_button" />

						<button name="button_refuse_revision_response" string="رفض"
							type="object" states="revision_response" groups="smart_hr.group_holidays_checker"
							icon="fa-times" class="oe_inline oe_stat_button" />

						<field name="state" widget="statusbar"
							statusbar_visible="draft,dm,audit,hrm,external_audit,revision,revision_response,done" />

					</header>
					<sheet>

						<group string="صاحب الطلب">
							<field name="date" readonly="1" />
							<field name="employee_id" required="1" readonly='1' />
							
						</group>
						<group col="4">
							<field name="holiday_status_id" required="1" />
							<field name="holidays_available_stock" attrs="{'invisible':[('state','=','done')]}" />
							<field name="raison" attrs="{'invisible':[('holiday_status_id','!=', %(data_hr_holiday_status_exceptional)d)]}" />
						</group>
						<group col="4">
							<field name="date_from" required="1"
								attrs="{'readonly':['|',('state','not in',['draft'])]}" />
							<field name="date_to" required="1"
								attrs="{'readonly':[('state','not in',['draft'])]}" />
							<field name="duration" />
						</group>
						<group col="4">
							<field name="num_outspeech"
								attrs="{'readonly':['|',('state','!=','external_audit')], 'invisible':[('state','not in',['external_audit','revision', 'revision_response','done'])]}" />
							<field name="date_outspeech"
								attrs="{'readonly':[('state','!=','external_audit')], 'invisible':[('state','not in',['external_audit','revision', 'revision_response','done'])]}" />
						</group>
						<group col="4">
							<field name="num_inspeech" groups="smart_hr.group_holidays_checker"
								attrs="{'readonly':['|',('state','!=','revision_response')], 'invisible':[('state','not in',['revision_response','done'])]}" />
							<field name="date_inspeech" groups="smart_hr.group_holidays_checker"
								attrs="{'readonly':[('state','!=','revision_response')], 'invisible':[('state','not in',['revision_response','done'])]}" />
						</group>
						<group>
							<field name="notes" string="ملاحظات" attrs="{'readonly':[('state','!=','draft')]}" />
						</group>
						<button name="%(report_hr_holidays_report)d" string="طباعة القرار" type="action"
							states="done" icon="fa-print" class="oe_inline oe_stat_button" />
						<div style="margin-top:15px;">
							<field name="message_ids" widget="mail_thread" readonly="1" />
						</div>
					</sheet>

				</form>
			</field>
		</record>
		<record model="ir.actions.act_window" id="action_hr_holidays">
			<field name="name">الطلبات</field>
			<field name="res_model">hr.holidays</field>
			<field name="view_type">form</field>
			<field name="view_mode">tree,form</field>
			<field name="context">{'readonly_by_pass': True}</field>
		</record>
		<menuitem id="hr_holidays_menu" name='طلبات الإجازة'  sequence="5"
			parent="menu_hr_holiday_root" action="action_hr_holidays" />




		<!-- hr holidays status inherit form -->
		<menuitem id="menu_hr_holidays_status_root" parent="hr_root_configuration"
			name="اجازات" sequence="8" />

		<record id="view_form_hr_holidays_status" model="ir.ui.view">
			<field name="name">hr.holidays.status.form</field>
			<field name="model">hr.holidays.status</field>
			<field name="inherit_id" ref="hr_holidays.edit_holiday_status_form" />
			<field name="arch" type="xml">
				<xpath expr="/form" position='replace'>
					<form string="نوع الأجازة">
						<sheet>
							<group>
								<field name="name" required="1" />
							</group>
							<group>
								<field name="entitlements" string="أنواع  الاستحقاقات">
									<tree editable="bottom">
										<field name="entitlment_category" required="1" />
										<field name="holiday_stock_default" />
										<field name="conditionnal" />
										<field name="periode" />
									</tree>
								</field>
							</group>
							<group>
								<field name="percentages">
									<tree editable="bottom" string="نسب الراتب المحتسبة">
										<field name="sequence" required="1" />
										<field name="periode" required="1" />
										<field name="salary_proportion" required="1" />
									</tree>
								</field>
							</group>
							<group>
								<field name="minimum" />
								<field name="maximum" />
								<field name="postponement_period" />
								<field name="color_name" />

							</group>
							<group>

								<field name="limit" string = "محدودة المدة"/>
								<field name="direct_decision" />
								<field name="external_decision" />
								<field name="direct_director_decision" />
								<field name="salary_spending" />
								<field name="employees_director_decision" />
								<field name="can_be_cancelled" />
								<field name="active" />
								<field name="deductible_normal_leave" />
								<field name="deductible_duration_service" />
								<field name="educ_lvl_req" />
								<field name="education_levels" attrs="{'invisible':[('educ_lvl_req', '=', False)]}"
									widget="many2many" />
								<field name="evaluation_condition" />
								<field name="assessments_required"
									attrs="{'invisible':[('evaluation_condition', '=', False)]}"
									widget="many2many" />
							</group>



						</sheet>
					</form>
				</xpath>
			</field>
		</record>
		<record id="view_tree_hr_holidays_status" model="ir.ui.view">
			<field name="name">hr.holidays.status.tree</field>
			<field name="model">hr.holidays.status</field>
			<field name="arch" type="xml">
				<tree string="أنواع الأجازات">
					<field name="name" />
				</tree>
			</field>
		</record>

		<record id="action_hr_holidays_status" model="ir.actions.act_window">
			<field name="name">أنواع الأجازات</field>
			<field name="res_model">hr.holidays.status</field>
			<field name="view_type">form</field>
			<field name="view_mode">tree,form</field>
			<field name="help" type="html">
				<p class="oe_view_nocontent_create">أنقر هنا للإضافة</p>
			</field>
		</record>
		<menuitem id="menu_hr_holidays_status" action="action_hr_holidays_status"
			parent="menu_hr_holidays_status_root" name="أنواع الأجازات" />


		<!-- تأجيل إجازة -->
		<record model="ir.ui.view" id="hr_job_delay_holiday_form">
			<field name="name">hr.delay.holiday.form</field>
			<field name="model">hr.delay.holiday</field>
			<field name="type">form</field>
			<field name="arch" type="xml">
				<form string="تأجيل إجازة">
					<sheet>
						<group col="4">
							<field name="date_from" />
							<field name="date_to" />
							<field name="delay_days" />
						</group>
					</sheet>
					<button name="action_delay_holiday_confirm" string="موافق"
						type="object"  />
				</form>
			</field>
		</record>

	</data>
</openerp>
